{
  "quinzena": {
    "de": "2026-05-01",
    "ate": "2026-05-15"
  },
  "geradoEm": "2026-05-08T20:12:50.085666",
  "planilhaArquivo": "2026-05-08-17-01_AnalisarPostagens-544407-20260507.xlsx",
  "resumo": {
    "ok": 76,
    "divergencias": 3,
    "divergenciasPedidos": 2,
    "soPlanilha": 24,
    "soFabric": 1,
    "nPlanilha": 103,
    "nFabric": 90,
    "totalPedidosPostagem": 4022.52,
    "totalPaVesti": 276.91,
    "totalGeralPostagem": 4299.43,
    "totalCobrarPedidos": 4424.77,
    "totalCobrarPa": 304.6,
    "totalCobrarMarcas": 4729.37,
    "custoDiogo": 4299.43,
    "diogoDetectado": false,
    "margemVesti": 429.94,
    "nPaVesti": 3
  },
  "paVesti": [
    {
      "data": "2026-05-06",
      "operador": "ONLOG RED",
      "modalidade": "ECONOPACK",
      "codigoInterno": "AA0097914325",
      "numeroNF": "11078758",
      "remetente": "PA VESTI",
      "cliente": "MARIA APARECIDA SANTANA LIMA",
      "clienteDoc": "22.982.386/0001-17",
      "cidade": "ILHÉUS",
      "uf": "BA",
      "status": "OBJETO EM TRANSFERÊNCIA - POR FAVOR AGUARDE",
      "postagem": 104.32
    },
    {
      "data": "2026-05-04",
      "operador": "ONLOG RED",
      "modalidade": "FASTPACK",
      "codigoInterno": "AA0097677950",
      "numeroNF": "009728685",
      "remetente": "PA VESTI",
      "cliente": "MARIANA BERNARDI JOIA",
      "clienteDoc": "08.143.870/0001-21",
      "cidade": "BRASÍLIA",
      "uf": "DF",
      "status": "ETIQUETA EMITIDA",
      "postagem": 68.27
    },
    {
      "data": "2026-05-04",
      "operador": "ONLOG RED",
      "modalidade": "ECONOPACK",
      "codigoInterno": "AA0097678427",
      "numeroNF": "007135648",
      "remetente": "VESTI",
      "cliente": "MARIA APARECIDA SANTANA LIMA",
      "clienteDoc": "22982386000117",
      "cidade": "ILHEUS",
      "uf": "BA",
      "status": "ETIQUETA EMITIDA",
      "postagem": 104.32
    }
  ],
  "cobrancaPorMarca": [
    {
      "domainId": "14035",
      "marca": "",
      "nPedidos": 53,
      "postagem": 1920.35,
      "cobrar": 2112.39
    },
    {
      "domainId": "1355848",
      "marca": "",
      "nPedidos": 15,
      "postagem": 804.8,
      "cobrar": 885.28
    },
    {
      "domainId": "1737229",
      "marca": "",
      "nPedidos": 10,
      "postagem": 455.17,
      "cobrar": 500.69
    },
    {
      "domainId": "268016",
      "marca": "",
      "nPedidos": 4,
      "postagem": 183.81,
      "cobrar": 202.19
    },
    {
      "domainId": "1514922",
      "marca": "",
      "nPedidos": 5,
      "postagem": 145.9,
      "cobrar": 160.49
    },
    {
      "domainId": "1956465",
      "marca": "",
      "nPedidos": 5,
      "postagem": 129.62,
      "cobrar": 142.58
    },
    {
      "domainId": "15",
      "marca": "",
      "nPedidos": 1,
      "postagem": 107.79,
      "cobrar": 118.57
    },
    {
      "domainId": "2032548",
      "marca": "",
      "nPedidos": 1,
      "postagem": 42.35,
      "cobrar": 46.59
    },
    {
      "domainId": "1893722",
      "marca": "",
      "nPedidos": 1,
      "postagem": 36.16,
      "cobrar": 39.78
    },
    {
      "domainId": "1305816",
      "marca": "",
      "nPedidos": 2,
      "postagem": 35.62,
      "cobrar": 39.18
    },
    {
      "domainId": "2018547",
      "marca": "",
      "nPedidos": 1,
      "postagem": 31.84,
      "cobrar": 35.02
    },
    {
      "domainId": "1562486",
      "marca": "",
      "nPedidos": 1,
      "postagem": 31.46,
      "cobrar": 34.61
    },
    {
      "domainId": "1528187",
      "marca": "",
      "nPedidos": 1,
      "postagem": 29.16,
      "cobrar": 32.08
    },
    {
      "domainId": "1439966",
      "marca": "",
      "nPedidos": 1,
      "postagem": 28.16,
      "cobrar": 30.98
    },
    {
      "domainId": "1700800",
      "marca": "",
      "nPedidos": 1,
      "postagem": 26.03,
      "cobrar": 28.63
    },
    {
      "domainId": "1805647",
      "marca": "",
      "nPedidos": 1,
      "postagem": 14.3,
      "cobrar": 15.73
    }
  ],
  "auditStatus": [
    {
      "orderNumber": 1034,
      "marca": " Era Uma Vez",
      "cliente": "Sandra",
      "statusMongo": "WAITING",
      "statusOnlog": "OBJETO CRIADO"
    },
    {
      "orderNumber": 1035,
      "marca": " Era Uma Vez",
      "cliente": "Samanta Da Rocha Silva Machado",
      "statusMongo": "WAITING",
      "statusOnlog": "OBJETO CRIADO"
    },
    {
      "orderNumber": 1036,
      "marca": " Era Uma Vez",
      "cliente": "Samanta Da Rocha Silva Machado",
      "statusMongo": "WAITING",
      "statusOnlog": "OBJETO CRIADO"
    },
    {
      "orderNumber": 377,
      "marca": "",
      "cliente": "Franciele Astrisi",
      "statusMongo": "WAITING",
      "statusOnlog": "OBJETO CRIADO"
    },
    {
      "orderNumber": 1039,
      "marca": " Era Uma Vez",
      "cliente": "Christine Sampaio",
      "statusMongo": "WAITING",
      "statusOnlog": "OBJETO CRIADO"
    },
    {
      "orderNumber": 1041,
      "marca": " Era Uma Vez",
      "cliente": "Gilmara Ferreira De Almeida",
      "statusMongo": "WAITING",
      "statusOnlog": "OBJETO CRIADO"
    },
    {
      "orderNumber": 4180,
      "marca": "Arary",
      "cliente": "Marcely Eduarda da Silva Amorim",
      "statusMongo": "WAITING",
      "statusOnlog": "OBJETO EM TRANSFERÊNCIA - POR FAVOR AGUARDE"
    },
    {
      "orderNumber": 4186,
      "marca": "Arary",
      "cliente": "Auda de Souza Guedes Pires ",
      "statusMongo": "WAITING",
      "statusOnlog": "OBJETO POSTADO APÓS O HORÁRIO LIMITE DA UNIDADE"
    },
    {
      "orderNumber": 6274,
      "marca": "Anne Blánc",
      "cliente": "Elenice Bazana De Souza",
      "statusMongo": "WAITING",
      "statusOnlog": "OBJETO CRIADO"
    },
    {
      "orderNumber": 6275,
      "marca": "Anne Blánc",
      "cliente": "Lucimar De Oliveira Quixaba",
      "statusMongo": "WAITING",
      "statusOnlog": "OBJETO CRIADO"
    },
    {
      "orderNumber": 6276,
      "marca": "Anne Blánc",
      "cliente": "Solange Barbosa De Almeida",
      "statusMongo": "WAITING",
      "statusOnlog": "OBJETO CRIADO"
    },
    {
      "orderNumber": 6277,
      "marca": "Anne Blánc",
      "cliente": "Jéssica Keli Bastos",
      "statusMongo": "WAITING",
      "statusOnlog": "OBJETO CRIADO"
    },
    {
      "orderNumber": 205,
      "marca": "Porã",
      "cliente": "Jaqueline",
      "statusMongo": "WAITING",
      "statusOnlog": "OBJETO CRIADO"
    },
    {
      "orderNumber": 10,
      "marca": "Liberô Style",
      "cliente": "Adriana Peres",
      "statusMongo": "WAITING",
      "statusOnlog": "OBJETO CRIADO"
    },
    {
      "orderNumber": 893,
      "marca": "KAESSI",
      "cliente": "Priscila M A Darini",
      "statusMongo": "WAITING",
      "statusOnlog": "OBJETO CRIADO"
    },
    {
      "orderNumber": 208,
      "marca": "Porã",
      "cliente": "Maria Sineide",
      "statusMongo": "WAITING",
      "statusOnlog": "OBJETO CRIADO"
    },
    {
      "orderNumber": 6283,
      "marca": "Anne Blánc",
      "cliente": "Gatta Vestuários Ltda",
      "statusMongo": "WAITING",
      "statusOnlog": "OBJETO CRIADO"
    },
    {
      "orderNumber": 6284,
      "marca": "Anne Blánc",
      "cliente": "Ane Noguti",
      "statusMongo": "WAITING",
      "statusOnlog": "OBJETO CRIADO"
    },
    {
      "orderNumber": 896,
      "marca": "KAESSI",
      "cliente": "Andrea M Oliveira",
      "statusMongo": "WAITING",
      "statusOnlog": "OBJETO CRIADO"
    },
    {
      "orderNumber": 6285,
      "marca": "Anne Blánc",
      "cliente": "Gina Karla Sobreira Nunes",
      "statusMongo": "WAITING",
      "statusOnlog": "OBJETO CRIADO"
    },
    {
      "orderNumber": 6289,
      "marca": "Anne Blánc",
      "cliente": "Liêz",
      "statusMongo": "WAITING",
      "statusOnlog": "OBJETO CRIADO"
    },
    {
      "orderNumber": 6291,
      "marca": "Anne Blánc",
      "cliente": "Carolina Regina Da Silva",
      "statusMongo": "WAITING",
      "statusOnlog": "OBJETO CRIADO"
    },
    {
      "orderNumber": 210,
      "marca": "Porã",
      "cliente": "Natalia Teixeira Da Silva",
      "statusMongo": "WAITING",
      "statusOnlog": "OBJETO CRIADO"
    },
    {
      "orderNumber": 6292,
      "marca": "Anne Blánc",
      "cliente": "Neuzete Barbosa",
      "statusMongo": "WAITING",
      "statusOnlog": "OBJETO CRIADO"
    },
    {
      "orderNumber": 6293,
      "marca": "Anne Blánc",
      "cliente": "Ivana Reis",
      "statusMongo": "WAITING",
      "statusOnlog": "OBJETO CRIADO"
    },
    {
      "orderNumber": 6294,
      "marca": "Anne Blánc",
      "cliente": "Andreia Luiz Dos Santos",
      "statusMongo": "WAITING",
      "statusOnlog": "OBJETO CRIADO"
    },
    {
      "orderNumber": 6295,
      "marca": "Anne Blánc",
      "cliente": "Ellen Biondi",
      "statusMongo": "WAITING",
      "statusOnlog": "OBJETO CRIADO"
    }
  ],
  "auditEtiqueta": [],
  "auditFrete": [
    {
      "orderNumber": 6283,
      "marca": "Anne Blánc",
      "cliente": "Gatta Vestuários Ltda",
      "postagem": 15.37,
      "esperado": 16.91,
      "biaMongo": 15.85,
      "diferenca": -1.06,
      "diferencaPct": 6.3
    }
  ],
  "auditResumo": {
    "statusAtrasado": 27,
    "semEtiqueta": 0,
    "freteDivergente": 1
  },
  "divergencias": [
    {
      "orderNumber": 3,
      "marca": "",
      "campo": "Cancelado",
      "planilha": "(postado pela Onlog)",
      "fabric": "CANCELADO no Vesti"
    },
    {
      "orderNumber": 3,
      "marca": "DoceVida ",
      "campo": "Cancelado",
      "planilha": "(postado pela Onlog)",
      "fabric": "CANCELADO no Vesti"
    },
    {
      "orderNumber": 4,
      "marca": "Asha Plus",
      "campo": "Cancelado",
      "planilha": "(postado pela Onlog)",
      "fabric": "CANCELADO no Vesti"
    }
  ],
  "soPlanilha": [
    {
      "codigoVolume": "1355848_4193",
      "orderNumber": "4193",
      "cliente": "LUCILENE VALERIA DA SILVA",
      "clienteDoc": "30253775000130",
      "cidade": "BETIM",
      "uf": "MG",
      "status": "ENTRADA NO CENTRO DE DISTRIBUIÇÃO",
      "postagem": 20.93,
      "data": "2026-05-06",
      "remetente": "ARARY",
      "valorDeclarado": 734.0
    },
    {
      "codigoVolume": "14035_6320",
      "orderNumber": "6320",
      "cliente": "MICHELE SILVA",
      "clienteDoc": "76936503691",
      "cidade": "BELO HORIZONTE",
      "uf": "MG",
      "status": "OBJETO CRIADO",
      "postagem": 19.95,
      "data": "2026-05-07",
      "remetente": "ANNE BLE1NC",
      "valorDeclarado": 316.0
    },
    {
      "codigoVolume": "268016_6751",
      "orderNumber": "6751",
      "cliente": "INDIANA SAN FERREIRA",
      "clienteDoc": "43763542000129",
      "cidade": "PORTO SEGURO",
      "uf": "BA",
      "status": "OBJETO EM TRANSFERÊNCIA - POR FAVOR AGUARDE",
      "postagem": 66.67,
      "data": "2026-05-06",
      "remetente": "CHOCOLATE DOCE",
      "valorDeclarado": 515.0
    },
    {
      "codigoVolume": "1893722_10",
      "orderNumber": "10",
      "cliente": "KELLY GOMES TOMELIN",
      "clienteDoc": "41264100000102",
      "cidade": "SINOP",
      "uf": "MT",
      "status": "ENCAMINHADO PARA O OPERADOR LOGÍSTICO",
      "postagem": 36.16,
      "data": "2026-05-05",
      "remetente": "SARA E MARI",
      "valorDeclarado": 515.6
    },
    {
      "codigoVolume": "1528187_13",
      "orderNumber": "13",
      "cliente": "SANDRA CARROZZO",
      "clienteDoc": "09093228803",
      "cidade": "MOGI MIRIM",
      "uf": "SP",
      "status": "OBJETO EM TRANSFERÊNCIA - POR FAVOR AGUARDE",
      "postagem": 29.16,
      "data": "2026-05-02",
      "remetente": "SANDY",
      "valorDeclarado": 990.0
    },
    {
      "codigoVolume": "268016_6750",
      "orderNumber": "6750",
      "cliente": "GIOVANNA YARZON",
      "clienteDoc": "55335196000167",
      "cidade": "CAMPO GRANDE",
      "uf": "MS",
      "status": "OBJETO POSTADO APÓS O HORÁRIO LIMITE DA UNIDADE",
      "postagem": 37.21,
      "data": "2026-05-06",
      "remetente": "CHOCOLATE DOCE",
      "valorDeclarado": 620.0
    },
    {
      "codigoVolume": "1805647_1256",
      "orderNumber": "1256",
      "cliente": "FRANCINELI ALCALE1",
      "clienteDoc": "31035734800",
      "cidade": "SANTA BE1RBARA D'OESTE",
      "uf": "SP",
      "status": "OBJETO POSTADO APÓS O HORÁRIO LIMITE DA UNIDADE",
      "postagem": 14.3,
      "data": "2026-05-06",
      "remetente": "CVL MODA - PLAZA POLO",
      "valorDeclarado": 261.4
    },
    {
      "codigoVolume": "14035_6297",
      "orderNumber": "6297",
      "cliente": "ANDREZZA SARCINELLI",
      "clienteDoc": "14530934780",
      "cidade": "VILA VELHA",
      "uf": "ES",
      "status": "OBJETO CRIADO",
      "postagem": 18.14,
      "data": "2026-05-06",
      "remetente": "ANNE BLE1NC",
      "valorDeclarado": 328.0
    },
    {
      "codigoVolume": "14035_6296",
      "orderNumber": "6296",
      "cliente": "BRUNA TAISLA",
      "clienteDoc": "10651693616",
      "cidade": "LAVRAS",
      "uf": "MG",
      "status": "OBJETO CRIADO",
      "postagem": 25.66,
      "data": "2026-05-06",
      "remetente": "ANNE BLE1NC",
      "valorDeclarado": 587.0
    },
    {
      "codigoVolume": "1305816_15",
      "orderNumber": "15",
      "cliente": "MATHEUS",
      "clienteDoc": "38155471802",
      "cidade": "SE3O PAULO",
      "uf": "SP",
      "status": "OBJETO CRIADO",
      "postagem": 12.28,
      "data": "2026-05-06",
      "remetente": "PALMEIRA",
      "valorDeclarado": 259.9
    },
    {
      "codigoVolume": "1355848_4194",
      "orderNumber": "4194",
      "cliente": "SILVANA ESCOBAR DE VASTO",
      "clienteDoc": "32174296000153",
      "cidade": "SOROCABA",
      "uf": "SP",
      "status": "ENTRADA NO CENTRO DE DISTRIBUIÇÃO",
      "postagem": 15.09,
      "data": "2026-05-06",
      "remetente": "ARARY",
      "valorDeclarado": 382.0
    },
    {
      "codigoVolume": "268016_6752",
      "orderNumber": "6752",
      "cliente": "MARCELY VALESCA DA SILVA CARDOSO",
      "clienteDoc": "54990271000160",
      "cidade": "MACAPE1",
      "uf": "AP",
      "status": "OBJETO CRIADO",
      "postagem": 50.73,
      "data": "2026-05-06",
      "remetente": "CHOCOLATE DOCE",
      "valorDeclarado": 1292.0
    },
    {
      "codigoVolume": "14035_6300",
      "orderNumber": "6300",
      "cliente": "JAMILA STOCO GOBBI JOSE",
      "clienteDoc": "06881444702",
      "cidade": "VITF3RIA",
      "uf": "ES",
      "status": "OBJETO CRIADO",
      "postagem": 17.94,
      "data": "2026-05-06",
      "remetente": "ANNE BLE1NC",
      "valorDeclarado": 350.0
    },
    {
      "codigoVolume": "14035_6306",
      "orderNumber": "6306",
      "cliente": "NATALIA PESSOA",
      "clienteDoc": "08017624646",
      "cidade": "CAETE9",
      "uf": "MG",
      "status": "OBJETO CRIADO",
      "postagem": 23.43,
      "data": "2026-05-06",
      "remetente": "ANNE BLE1NC",
      "valorDeclarado": 505.0
    },
    {
      "codigoVolume": "14035_6308",
      "orderNumber": "6308",
      "cliente": "EDUARDA LIMA",
      "clienteDoc": "62523484000100",
      "cidade": "FRANCA",
      "uf": "SP",
      "status": "OBJETO CRIADO",
      "postagem": 17.27,
      "data": "2026-05-06",
      "remetente": "ANNE BLE1NC",
      "valorDeclarado": 696.0
    },
    {
      "codigoVolume": "1355848_4195",
      "orderNumber": "4195",
      "cliente": "OLIVEIRA",
      "clienteDoc": "03167504170",
      "cidade": "BRASEDLIA",
      "uf": "DF",
      "status": "OBJETO CRIADO",
      "postagem": 31.87,
      "data": "2026-05-07",
      "remetente": "ARARY",
      "valorDeclarado": 620.0
    },
    {
      "codigoVolume": "14035_6304",
      "orderNumber": "6304",
      "cliente": "NATE1LIA CORREIA",
      "clienteDoc": "03336228123",
      "cidade": "BRASEDLIA",
      "uf": "DF",
      "status": "OBJETO CRIADO",
      "postagem": 40.04,
      "data": "2026-05-06",
      "remetente": "ANNE BLE1NC",
      "valorDeclarado": 957.0
    },
    {
      "codigoVolume": "14035_6298",
      "orderNumber": "6298",
      "cliente": "KATIA PEDRA",
      "clienteDoc": "01490124110",
      "cidade": "CAMPO GRANDE",
      "uf": "MS",
      "status": "OBJETO CRIADO",
      "postagem": 36.96,
      "data": "2026-05-06",
      "remetente": "ANNE BLE1NC",
      "valorDeclarado": 551.0
    },
    {
      "codigoVolume": "14035_6309",
      "orderNumber": "6309",
      "cliente": "LAURA DE ALMEIDA MAGALHAES FURTADO MIRANDA",
      "clienteDoc": "02187705617",
      "cidade": "RIO DE JANEIRO",
      "uf": "RJ",
      "status": "ETIQUETA EMITIDA",
      "postagem": 59.52,
      "data": "2026-05-06",
      "remetente": "ANNE BLE1NC",
      "valorDeclarado": 933.0
    },
    {
      "codigoVolume": "1305816_14",
      "orderNumber": "14",
      "cliente": "TESTE PEDIDO SUPORTE VESTI",
      "clienteDoc": "88174196000181",
      "cidade": "PORTO ALEGRE",
      "uf": "RS",
      "status": "OBJETO CRIADO",
      "postagem": 23.34,
      "data": "2026-05-06",
      "remetente": "PALMEIRA",
      "valorDeclarado": 519.8
    },
    {
      "codigoVolume": "1956465_211",
      "orderNumber": "211",
      "cliente": "VIVIAM CRISTINA FERNANDES DE SOUZA",
      "clienteDoc": "30134545800",
      "cidade": "SANTA RITA DO PASSA QUATRO",
      "uf": "SP",
      "status": "OBJETO CRIADO",
      "postagem": 52.72,
      "data": "2026-05-06",
      "remetente": "PORE3",
      "valorDeclarado": 240.0
    },
    {
      "codigoVolume": "14035_6315",
      "orderNumber": "6315",
      "cliente": "VANESSA LISBOA",
      "clienteDoc": "31267163852",
      "cidade": "AMPARO",
      "uf": "SP",
      "status": "OBJETO CRIADO",
      "postagem": 31.26,
      "data": "2026-05-06",
      "remetente": "ANNE BLE1NC",
      "valorDeclarado": 506.0
    },
    {
      "codigoVolume": "14035_6262",
      "orderNumber": "6262",
      "cliente": "IVANA MEDEIROS",
      "clienteDoc": "43043022000141",
      "cidade": "RECIFE",
      "uf": "PE",
      "status": "TRANSFERENCIA",
      "postagem": 56.67,
      "data": "2026-05-06",
      "remetente": "ANNE BLE1NC",
      "valorDeclarado": 500.0
    },
    {
      "codigoVolume": "1956465_215",
      "orderNumber": "215",
      "cliente": "MARIA SANTOS",
      "clienteDoc": "76944310082",
      "cidade": "GRAVATAED",
      "uf": "RS",
      "status": "OBJETO CRIADO",
      "postagem": 20.72,
      "data": "2026-05-06",
      "remetente": "PORE3",
      "valorDeclarado": 201.0
    }
  ],
  "soFabric": [
    {
      "data": "2026-05-04",
      "orderNumber": 4174,
      "marca": "Arary",
      "cliente": "ENI DA COSTA",
      "cidade": "Contagem",
      "uf": "MG",
      "cancelado": false,
      "status": "DELIVERED",
      "valor": 1137.13
    }
  ],
  "_planilhaSnapshot": {
    "planilha": {
      "14035_6213": {
        "codigoVolume": "14035_6213",
        "orderNumber": "6213",
        "domainId": "14035",
        "cliente": "ELISANGELA STEIMBACH MATTOS",
        "clienteDoc": "05452981993",
        "cidade": "PALHOE7A",
        "uf": "SC",
        "status": "ENCAMINHADO PARA O OPERADOR LOGÍSTICO",
        "data": "2026-05-01",
        "postagem": 36.05,
        "remetente": "ANNE BLE1NC",
        "valorDeclarado": 754.0
      },
      "14035_6215": {
        "codigoVolume": "14035_6215",
        "orderNumber": "6215",
        "domainId": "14035",
        "cliente": "VANESSA RODRIGUES RIBEIRO DIAS",
        "clienteDoc": "02791753532",
        "cidade": "BREJF5ES",
        "uf": "BA",
        "status": "ENCAMINHADO PARA O OPERADOR LOGÍSTICO",
        "data": "2026-05-01",
        "postagem": 80.93,
        "remetente": "ANNE BLE1NC",
        "valorDeclarado": 1351.7
      },
      "14035_6216": {
        "codigoVolume": "14035_6216",
        "orderNumber": "6216",
        "domainId": "14035",
        "cliente": "NATE1LIA CORREIA",
        "clienteDoc": "03336228123",
        "cidade": "BRASEDLIA",
        "uf": "DF",
        "status": "ENCAMINHADO PARA O OPERADOR LOGÍSTICO",
        "data": "2026-05-01",
        "postagem": 40.2,
        "remetente": "ANNE BLE1NC",
        "valorDeclarado": 762.0
      },
      "14035_6217": {
        "codigoVolume": "14035_6217",
        "orderNumber": "6217",
        "domainId": "14035",
        "cliente": "BRUNA ALMEIDA RAMOS",
        "clienteDoc": "08894233421",
        "cidade": "RECIFE",
        "uf": "PE",
        "status": "ENTRADA NO CENTRO DE DISTRIBUIÇÃO",
        "data": "2026-05-01",
        "postagem": 36.49,
        "remetente": "ANNE BLE1NC",
        "valorDeclarado": 527.0
      },
      "1514922_1034": {
        "codigoVolume": "1514922_1034",
        "orderNumber": "1034",
        "domainId": "1514922",
        "cliente": "SANDRA",
        "clienteDoc": "21097693000152",
        "cidade": "ITAQUAQUECETUBA",
        "uf": "SP",
        "status": "OBJETO CRIADO",
        "data": "2026-05-01",
        "postagem": 20.0,
        "remetente": "ERA UMA VEZ",
        "valorDeclarado": 353.66
      },
      "1514922_1035": {
        "codigoVolume": "1514922_1035",
        "orderNumber": "1035",
        "domainId": "1514922",
        "cliente": "SAMANTA DA ROCHA SILVA MACHADO",
        "clienteDoc": "10362972923",
        "cidade": "CURITIBA",
        "uf": "PR",
        "status": "OBJETO CRIADO",
        "data": "2026-05-01",
        "postagem": 44.14,
        "remetente": "ERA UMA VEZ",
        "valorDeclarado": 325.15
      },
      "1514922_1036": {
        "codigoVolume": "1514922_1036",
        "orderNumber": "1036",
        "domainId": "1514922",
        "cliente": "SAMANTA DA ROCHA SILVA MACHADO",
        "clienteDoc": "10362972923",
        "cidade": "CURITIBA",
        "uf": "PR",
        "status": "OBJETO CRIADO",
        "data": "2026-05-01",
        "postagem": 38.91,
        "remetente": "ERA UMA VEZ",
        "valorDeclarado": 346.96
      },
      "14035_6218": {
        "codigoVolume": "14035_6218",
        "orderNumber": "6218",
        "domainId": "14035",
        "cliente": "MARIANA ALMEIDA CUNHA",
        "clienteDoc": "13699906779",
        "cidade": "RIO DE JANEIRO",
        "uf": "RJ",
        "status": "ENTRADA NO CENTRO DE DISTRIBUIÇÃO",
        "data": "2026-05-01",
        "postagem": 23.29,
        "remetente": "ANNE BLE1NC",
        "valorDeclarado": 573.0
      },
      "14035_6219": {
        "codigoVolume": "14035_6219",
        "orderNumber": "6219",
        "domainId": "14035",
        "cliente": "ROBERTA FRANCO",
        "clienteDoc": "08325832789",
        "cidade": "RIO DE JANEIRO",
        "uf": "RJ",
        "status": "ENTRADA NO CENTRO DE DISTRIBUIÇÃO",
        "data": "2026-05-01",
        "postagem": 17.76,
        "remetente": "ANNE BLE1NC",
        "valorDeclarado": 320.0
      },
      "1700800_377": {
        "codigoVolume": "1700800_377",
        "orderNumber": "377",
        "domainId": "1700800",
        "cliente": "FRANCIELE ASTRISI",
        "clienteDoc": "66503427000110",
        "cidade": "IRINEF3POLIS",
        "uf": "SC",
        "status": "OBJETO CRIADO",
        "data": "2026-05-01",
        "postagem": 26.03,
        "remetente": "PLANETY CAT JEANS",
        "valorDeclarado": 325.0
      },
      "14035_6221": {
        "codigoVolume": "14035_6221",
        "orderNumber": "6221",
        "domainId": "14035",
        "cliente": "HELIA MARIZA PEREIRA",
        "clienteDoc": "25953206615",
        "cidade": "SANTOS DUMONT",
        "uf": "MG",
        "status": "ENTRADA NO CENTRO DE DISTRIBUIÇÃO",
        "data": "2026-05-01",
        "postagem": 66.41,
        "remetente": "ANNE BLE1NC",
        "valorDeclarado": 1165.0
      },
      "14035_6222": {
        "codigoVolume": "14035_6222",
        "orderNumber": "6222",
        "domainId": "14035",
        "cliente": "PRISCILA CALEGARI",
        "clienteDoc": "33231181895",
        "cidade": "BARUERI",
        "uf": "SP",
        "status": "ENTRADA NO CENTRO DE DISTRIBUIÇÃO",
        "data": "2026-05-01",
        "postagem": 15.71,
        "remetente": "ANNE BLE1NC",
        "valorDeclarado": 436.0
      },
      "14035_6226": {
        "codigoVolume": "14035_6226",
        "orderNumber": "6226",
        "domainId": "14035",
        "cliente": "PATRICIA CORREA",
        "clienteDoc": "00892315385",
        "cidade": "SE3O LUEDS",
        "uf": "MA",
        "status": "TRANSFERENCIA",
        "data": "2026-05-01",
        "postagem": 35.63,
        "remetente": "ANNE BLE1NC",
        "valorDeclarado": 501.99
      },
      "14035_6227": {
        "codigoVolume": "14035_6227",
        "orderNumber": "6227",
        "domainId": "14035",
        "cliente": "GENY BASTOS P",
        "clienteDoc": "80963927787",
        "cidade": "SE3O JOE3O DE MERITI",
        "uf": "RJ",
        "status": "OBJETO CRIADO",
        "data": "2026-05-02",
        "postagem": 49.3,
        "remetente": "ANNE BLE1NC",
        "valorDeclarado": 625.0
      },
      "1528187_13": {
        "codigoVolume": "1528187_13",
        "orderNumber": "13",
        "domainId": "1528187",
        "cliente": "SANDRA CARROZZO",
        "clienteDoc": "09093228803",
        "cidade": "MOGI MIRIM",
        "uf": "SP",
        "status": "OBJETO EM TRANSFERÊNCIA - POR FAVOR AGUARDE",
        "data": "2026-05-02",
        "postagem": 29.16,
        "remetente": "SANDY",
        "valorDeclarado": 990.0
      },
      "14035_6228": {
        "codigoVolume": "14035_6228",
        "orderNumber": "6228",
        "domainId": "14035",
        "cliente": "POLLYANNA NUNES DE OLIVEIRA",
        "clienteDoc": "02477488112",
        "cidade": "ANE1POLIS",
        "uf": "GO",
        "status": "TRANSFERENCIA",
        "data": "2026-05-02",
        "postagem": 52.31,
        "remetente": "ANNE BLE1NC",
        "valorDeclarado": 1297.0
      },
      "1514922_1039": {
        "codigoVolume": "1514922_1039",
        "orderNumber": "1039",
        "domainId": "1514922",
        "cliente": "CHRISTINE SAMPAIO",
        "clienteDoc": "61608079000122",
        "cidade": "CURITIBA",
        "uf": "PR",
        "status": "OBJETO CRIADO",
        "data": "2026-05-02",
        "postagem": 21.12,
        "remetente": "ERA UMA VEZ",
        "valorDeclarado": 464.82
      },
      "1737229_882": {
        "codigoVolume": "1737229_882",
        "orderNumber": "882",
        "domainId": "1737229",
        "cliente": "NILCELIA",
        "clienteDoc": "96132523987",
        "cidade": "PINHAIS",
        "uf": "PR",
        "status": "ENTRADA NO CENTRO DE DISTRIBUIÇÃO",
        "data": "2026-05-02",
        "postagem": 25.38,
        "remetente": "KAESSI",
        "valorDeclarado": 540.0
      },
      "14035_6232": {
        "codigoVolume": "14035_6232",
        "orderNumber": "6232",
        "domainId": "14035",
        "cliente": "ELLAYNE CAVALCANTI SILVA DOS SANTOS",
        "clienteDoc": "07975443484",
        "cidade": "MACEIF3",
        "uf": "AL",
        "status": "TRANSFERENCIA",
        "data": "2026-05-02",
        "postagem": 51.89,
        "remetente": "ANNE BLE1NC",
        "valorDeclarado": 796.9
      },
      "1737229_883": {
        "codigoVolume": "1737229_883",
        "orderNumber": "883",
        "domainId": "1737229",
        "cliente": "DANIELY MALTA",
        "clienteDoc": "19983906000100",
        "cidade": "SE3O JOSE9 DOS CAMPOS",
        "uf": "SP",
        "status": "OBJETO EM TRANSFERÊNCIA - POR FAVOR AGUARDE",
        "data": "2026-05-03",
        "postagem": 29.66,
        "remetente": "KAESSI",
        "valorDeclarado": 918.0
      },
      "14035_6234": {
        "codigoVolume": "14035_6234",
        "orderNumber": "6234",
        "domainId": "14035",
        "cliente": "VANESSA LISBOA",
        "clienteDoc": "31267163852",
        "cidade": "AMPARO",
        "uf": "SP",
        "status": "OBJETO EM TRANSFERÊNCIA - POR FAVOR AGUARDE",
        "data": "2026-05-03",
        "postagem": 29.26,
        "remetente": "ANNE BLE1NC",
        "valorDeclarado": 306.0
      },
      "1514922_1041": {
        "codigoVolume": "1514922_1041",
        "orderNumber": "1041",
        "domainId": "1514922",
        "cliente": "GILMARA FERREIRA DE ALMEIDA",
        "clienteDoc": "06844646755",
        "cidade": "PETRF3POLIS",
        "uf": "RJ",
        "status": "OBJETO CRIADO",
        "data": "2026-05-03",
        "postagem": 21.73,
        "remetente": "ERA UMA VEZ",
        "valorDeclarado": 438.48
      },
      "1737229_884": {
        "codigoVolume": "1737229_884",
        "orderNumber": "884",
        "domainId": "1737229",
        "cliente": "JANETE MARIA CAVALLI PRESTES",
        "clienteDoc": "30054800000156",
        "cidade": "PORTO ALEGRE",
        "uf": "RS",
        "status": "ENTRADA NO CENTRO DE DISTRIBUIÇÃO",
        "data": "2026-05-03",
        "postagem": 26.42,
        "remetente": "KAESSI",
        "valorDeclarado": 734.0
      },
      "14035_6236": {
        "codigoVolume": "14035_6236",
        "orderNumber": "6236",
        "domainId": "14035",
        "cliente": "ESPAE7O SUSY FARIA",
        "clienteDoc": "59434572000121",
        "cidade": "ARARAQUARA",
        "uf": "SP",
        "status": "ENTRADA NO CENTRO DE DISTRIBUIÇÃO",
        "data": "2026-05-03",
        "postagem": 15.66,
        "remetente": "ANNE BLE1NC",
        "valorDeclarado": 335.0
      },
      "14035_6237": {
        "codigoVolume": "14035_6237",
        "orderNumber": "6237",
        "domainId": "14035",
        "cliente": "RAQUEL LEITE",
        "clienteDoc": "05164963442",
        "cidade": "JOE3O PESSOA",
        "uf": "PB",
        "status": "TRANSFERENCIA",
        "data": "2026-05-03",
        "postagem": 39.5,
        "remetente": "ANNE BLE1NC",
        "valorDeclarado": 630.0
      },
      "1737229_885": {
        "codigoVolume": "1737229_885",
        "orderNumber": "885",
        "domainId": "1737229",
        "cliente": "FABIANA AMORIM KUASNE",
        "clienteDoc": "04128519979",
        "cidade": "LONDRINA",
        "uf": "PR",
        "status": "ENTRADA NO CENTRO DE DISTRIBUIÇÃO",
        "data": "2026-05-04",
        "postagem": 38.78,
        "remetente": "KAESSI",
        "valorDeclarado": 803.0
      },
      "1355848_4158": {
        "codigoVolume": "1355848_4158",
        "orderNumber": "4158",
        "domainId": "1355848",
        "cliente": "ADRIANA SARAIVA DE SA",
        "clienteDoc": "71266097368",
        "cidade": "TERESINA",
        "uf": "PI",
        "status": "ENTRADA NO CENTRO DE DISTRIBUIÇÃO",
        "data": "2026-05-04",
        "postagem": 38.16,
        "remetente": "ARARY",
        "valorDeclarado": 804.0
      },
      "1355848_4152": {
        "codigoVolume": "1355848_4152",
        "orderNumber": "4152",
        "domainId": "1355848",
        "cliente": "VANESSA BACCA",
        "clienteDoc": "28453758832",
        "cidade": "ARTUR NOGUEIRA",
        "uf": "SP",
        "status": "ENTRADA NO CENTRO DE DISTRIBUIÇÃO",
        "data": "2026-05-04",
        "postagem": 18.38,
        "remetente": "ARARY",
        "valorDeclarado": 668.0
      },
      "14035_6239": {
        "codigoVolume": "14035_6239",
        "orderNumber": "6239",
        "domainId": "14035",
        "cliente": "JUCILENE NASCIMENTO",
        "clienteDoc": "62539396291",
        "cidade": "BELE9M",
        "uf": "PA",
        "status": "TRANSFERENCIA",
        "data": "2026-05-04",
        "postagem": 33.78,
        "remetente": "ANNE BLE1NC",
        "valorDeclarado": 470.0
      },
      "1355848_4164": {
        "codigoVolume": "1355848_4164",
        "orderNumber": "4164",
        "domainId": "1355848",
        "cliente": "VILSE GABBIATI MENEGHETI",
        "clienteDoc": "28534239134",
        "cidade": "DOURADOS",
        "uf": "MS",
        "status": "OBJETO EM TRANSFERÊNCIA - POR FAVOR AGUARDE",
        "data": "2026-05-04",
        "postagem": 76.57,
        "remetente": "ARARY",
        "valorDeclarado": 1081.0
      },
      "1355848_4167": {
        "codigoVolume": "1355848_4167",
        "orderNumber": "4167",
        "domainId": "1355848",
        "cliente": "FRANCINE FRANE7A AMUI",
        "clienteDoc": "60367776634",
        "cidade": "SACRAMENTO",
        "uf": "MG",
        "status": "ARQUIVO RECEBIDO",
        "data": "2026-05-04",
        "postagem": 55.5,
        "remetente": "ARARY",
        "valorDeclarado": 1378.0
      },
      "15_562": {
        "codigoVolume": "15_562",
        "orderNumber": "562",
        "domainId": "15",
        "cliente": "CRISTIANE NASCIMENTO DIAS",
        "clienteDoc": "34595659857",
        "cidade": "PRESIDENTE EPITE1CIO",
        "uf": "SP",
        "status": "OBJETO EM TRANSFERÊNCIA - POR FAVOR AGUARDE",
        "data": "2026-05-04",
        "postagem": 107.79,
        "remetente": "MURANO JEANS",
        "valorDeclarado": 1679.79
      },
      "1355848_4177": {
        "codigoVolume": "1355848_4177",
        "orderNumber": "4177",
        "domainId": "1355848",
        "cliente": "PATRCIA NEVES",
        "clienteDoc": "33776495000102",
        "cidade": "RIO DE JANEIRO",
        "uf": "RJ",
        "status": "TRANSFERENCIA",
        "data": "2026-05-04",
        "postagem": 45.93,
        "remetente": "ARARY",
        "valorDeclarado": 516.0
      },
      "1355848_4160": {
        "codigoVolume": "1355848_4160",
        "orderNumber": "4160",
        "domainId": "1355848",
        "cliente": "DANIELLE BORETTI ANTUNES",
        "clienteDoc": "31168202876",
        "cidade": "ITAPIRA",
        "uf": "SP",
        "status": "OBJETO EM TRANSFERÊNCIA - POR FAVOR AGUARDE",
        "data": "2026-05-04",
        "postagem": 59.5,
        "remetente": "ARARY",
        "valorDeclarado": 2092.0
      },
      "14035_6245": {
        "codigoVolume": "14035_6245",
        "orderNumber": "6245",
        "domainId": "14035",
        "cliente": "DANIELE ARSENE ROJAS",
        "clienteDoc": "84838981104",
        "cidade": "DOURADOS",
        "uf": "MS",
        "status": "ENTRADA NO CENTRO DE DISTRIBUIÇÃO",
        "data": "2026-05-04",
        "postagem": 26.02,
        "remetente": "ANNE BLE1NC",
        "valorDeclarado": 623.0
      },
      "1355848_4159": {
        "codigoVolume": "1355848_4159",
        "orderNumber": "4159",
        "domainId": "1355848",
        "cliente": "CARMELLA MODAS",
        "clienteDoc": "07902069000150",
        "cidade": "CAMPINAS",
        "uf": "SP",
        "status": "OBJETO EM TRANSFERÊNCIA - POR FAVOR AGUARDE",
        "data": "2026-05-04",
        "postagem": 36.94,
        "remetente": "ARARY",
        "valorDeclarado": 1646.0
      },
      "14035_6248": {
        "codigoVolume": "14035_6248",
        "orderNumber": "6248",
        "domainId": "14035",
        "cliente": "ADALGISA MARTINS DE SOUZA",
        "clienteDoc": "09627238864",
        "cidade": "AVARE9",
        "uf": "SP",
        "status": "ENTRADA NO CENTRO DE DISTRIBUIÇÃO",
        "data": "2026-05-04",
        "postagem": 21.61,
        "remetente": "ANNE BLE1NC",
        "valorDeclarado": 882.0
      },
      "1355848_4180": {
        "codigoVolume": "1355848_4180",
        "orderNumber": "4180",
        "domainId": "1355848",
        "cliente": "MARCELY EDUARDA DA SILVA AMORIM",
        "clienteDoc": "01834470269",
        "cidade": "JUNDIAED",
        "uf": "SP",
        "status": "OBJETO EM TRANSFERÊNCIA - POR FAVOR AGUARDE",
        "data": "2026-05-04",
        "postagem": 23.1,
        "remetente": "ARARY",
        "valorDeclarado": 664.0
      },
      "14035_6250": {
        "codigoVolume": "14035_6250",
        "orderNumber": "6250",
        "domainId": "14035",
        "cliente": "RAFAELA DE MELO RESENDE",
        "clienteDoc": "07406705654",
        "cidade": "PRADOS",
        "uf": "MG",
        "status": "OBJETO CRIADO",
        "data": "2026-05-04",
        "postagem": 23.36,
        "remetente": "ANNE BLE1NC",
        "valorDeclarado": 493.0
      },
      "14035_6251": {
        "codigoVolume": "14035_6251",
        "orderNumber": "6251",
        "domainId": "14035",
        "cliente": "NATE1LIA CORREIA",
        "clienteDoc": "03336228123",
        "cidade": "BRASEDLIA",
        "uf": "DF",
        "status": "OBJETO CRIADO",
        "data": "2026-05-04",
        "postagem": 37.67,
        "remetente": "ANNE BLE1NC",
        "valorDeclarado": 720.0
      },
      "14035_6253": {
        "codigoVolume": "14035_6253",
        "orderNumber": "6253",
        "domainId": "14035",
        "cliente": "VANESSA CALAMITA",
        "clienteDoc": "39048374863",
        "cidade": "EMBU DAS ARTES",
        "uf": "SP",
        "status": "ENTRADA NO CENTRO DE DISTRIBUIÇÃO",
        "data": "2026-05-04",
        "postagem": 15.0,
        "remetente": "ANNE BLE1NC",
        "valorDeclarado": 225.0
      },
      "2018547_3": {
        "codigoVolume": "2018547_3",
        "orderNumber": "3",
        "domainId": "2018547",
        "cliente": "USUC1RIO TESTE VESTI",
        "clienteDoc": "81803653000100",
        "cidade": "SE3O PAULO",
        "uf": "SP",
        "status": "OBJETO CRIADO",
        "data": "2026-05-04",
        "postagem": 31.84,
        "remetente": "DOCEVIDA",
        "valorDeclarado": 1005.0
      },
      "14035_6256": {
        "codigoVolume": "14035_6256",
        "orderNumber": "6256",
        "domainId": "14035",
        "cliente": "EDUARDA LIMA",
        "clienteDoc": "62523484000100",
        "cidade": "FRANCA",
        "uf": "SP",
        "status": "ENTRADA NO CENTRO DE DISTRIBUIÇÃO",
        "data": "2026-05-04",
        "postagem": 17.82,
        "remetente": "ANNE BLE1NC",
        "valorDeclarado": 695.0
      },
      "14035_6258": {
        "codigoVolume": "14035_6258",
        "orderNumber": "6258",
        "domainId": "14035",
        "cliente": "LARISSA CERQUEIRA",
        "clienteDoc": "30982277000128",
        "cidade": "SALVADOR",
        "uf": "BA",
        "status": "ENCAMINHADO PARA O OPERADOR LOGÍSTICO",
        "data": "2026-05-04",
        "postagem": 91.65,
        "remetente": "ANNE BLE1NC",
        "valorDeclarado": 949.0
      },
      "1737229_888": {
        "codigoVolume": "1737229_888",
        "orderNumber": "888",
        "domainId": "1737229",
        "cliente": "ZENOBIA DANTAS REGO NETA",
        "clienteDoc": "05629897306",
        "cidade": "SE3O PAULO",
        "uf": "SP",
        "status": "OBJETO CRIADO",
        "data": "2026-05-04",
        "postagem": 93.67,
        "remetente": "KAESSI",
        "valorDeclarado": 1958.0
      },
      "14035_6265": {
        "codigoVolume": "14035_6265",
        "orderNumber": "6265",
        "domainId": "14035",
        "cliente": "AMANDA DE JESUS SANTANA",
        "clienteDoc": "29101052888",
        "cidade": "SANTOS",
        "uf": "SP",
        "status": "ENTRADA NO CENTRO DE DISTRIBUIÇÃO",
        "data": "2026-05-04",
        "postagem": 21.2,
        "remetente": "ANNE BLE1NC",
        "valorDeclarado": 525.0
      },
      "1737229_890": {
        "codigoVolume": "1737229_890",
        "orderNumber": "890",
        "domainId": "1737229",
        "cliente": "ANA CLAUDIA SOUZA",
        "clienteDoc": "35569648000168",
        "cidade": "ALTAMIRA",
        "uf": "PA",
        "status": "OBJETO CRIADO",
        "data": "2026-05-04",
        "postagem": 60.12,
        "remetente": "KAESSI",
        "valorDeclarado": 600.0
      },
      "14035_6267": {
        "codigoVolume": "14035_6267",
        "orderNumber": "6267",
        "domainId": "14035",
        "cliente": "JANETE BARBOSA GONALVES",
        "clienteDoc": "72750308291",
        "cidade": "PORTO VELHO",
        "uf": "RO",
        "status": "OBJETO CRIADO",
        "data": "2026-05-04",
        "postagem": 40.1,
        "remetente": "ANNE BLE1NC",
        "valorDeclarado": 850.0
      },
      "14035_6268": {
        "codigoVolume": "14035_6268",
        "orderNumber": "6268",
        "domainId": "14035",
        "cliente": "ANA BEATRIZ MOOR",
        "clienteDoc": "06245000556",
        "cidade": "SALVADOR",
        "uf": "BA",
        "status": "ENTRADA NO CENTRO DE DISTRIBUIÇÃO",
        "data": "2026-05-04",
        "postagem": 25.11,
        "remetente": "ANNE BLE1NC",
        "valorDeclarado": 324.0
      },
      "14035_6270": {
        "codigoVolume": "14035_6270",
        "orderNumber": "6270",
        "domainId": "14035",
        "cliente": "THATYANY DE SENA BARROS",
        "clienteDoc": "08926579603",
        "cidade": "CORONEL FABRICIANO",
        "uf": "MG",
        "status": "ENTRADA",
        "data": "2026-05-04",
        "postagem": 55.7,
        "remetente": "ANNE BLE1NC",
        "valorDeclarado": 1187.0
      },
      "1737229_891": {
        "codigoVolume": "1737229_891",
        "orderNumber": "891",
        "domainId": "1737229",
        "cliente": "CRISTIANE GODOY",
        "clienteDoc": "30844692883",
        "cidade": "SANTA BE1RBARA D'OESTE",
        "uf": "SP",
        "status": "ETIQUETA EMITIDA",
        "data": "2026-05-05",
        "postagem": 19.75,
        "remetente": "KAESSI",
        "valorDeclarado": 503.0
      },
      "1737229_892": {
        "codigoVolume": "1737229_892",
        "orderNumber": "892",
        "domainId": "1737229",
        "cliente": "CARLIENE GUEDES MONTEIRO",
        "clienteDoc": "14015298608",
        "cidade": "BELO HORIZONTE",
        "uf": "MG",
        "status": "OBJETO CRIADO",
        "data": "2026-05-05",
        "postagem": 93.08,
        "remetente": "KAESSI",
        "valorDeclarado": 1190.0
      },
      "1355848_4186": {
        "codigoVolume": "1355848_4186",
        "orderNumber": "4186",
        "domainId": "1355848",
        "cliente": "AUDA DE SOUZA GUEDES PIRES",
        "clienteDoc": "92459765800",
        "cidade": "ASSIS",
        "uf": "SP",
        "status": "OBJETO POSTADO APÓS O HORÁRIO LIMITE DA UNIDADE",
        "data": "2026-05-05",
        "postagem": 40.31,
        "remetente": "ARARY",
        "valorDeclarado": 1142.0
      },
      "14035_6274": {
        "codigoVolume": "14035_6274",
        "orderNumber": "6274",
        "domainId": "14035",
        "cliente": "ELENICE BAZANA DE SOUZA",
        "clienteDoc": "03963826819",
        "cidade": "CACONDE",
        "uf": "SP",
        "status": "OBJETO CRIADO",
        "data": "2026-05-05",
        "postagem": 17.77,
        "remetente": "ANNE BLE1NC",
        "valorDeclarado": 608.0
      },
      "14035_6223": {
        "codigoVolume": "14035_6223",
        "orderNumber": "6223",
        "domainId": "14035",
        "cliente": "NILVA ROSA DE FREITAS",
        "clienteDoc": "41133757120",
        "cidade": "VE1RZEA GRANDE",
        "uf": "MT",
        "status": "ENCAMINHADO PARA O OPERADOR LOGÍSTICO",
        "data": "2026-05-05",
        "postagem": 39.08,
        "remetente": "ANNE BLE1NC",
        "valorDeclarado": 492.0
      },
      "14035_6244": {
        "codigoVolume": "14035_6244",
        "orderNumber": "6244",
        "domainId": "14035",
        "cliente": "ANA REGINA SCHNEIDER",
        "clienteDoc": "49977865000",
        "cidade": "CRUZEIRO DO SUL",
        "uf": "RS",
        "status": "ENTRADA NO CENTRO DE DISTRIBUIÇÃO",
        "data": "2026-05-05",
        "postagem": 64.78,
        "remetente": "ANNE BLE1NC",
        "valorDeclarado": 1078.0
      },
      "14035_6275": {
        "codigoVolume": "14035_6275",
        "orderNumber": "6275",
        "domainId": "14035",
        "cliente": "LUCIMAR DE OLIVEIRA QUIXABA",
        "clienteDoc": "42880262372",
        "cidade": "TERESINA",
        "uf": "PI",
        "status": "OBJETO CRIADO",
        "data": "2026-05-05",
        "postagem": 35.88,
        "remetente": "ANNE BLE1NC",
        "valorDeclarado": 424.0
      },
      "14035_6276": {
        "codigoVolume": "14035_6276",
        "orderNumber": "6276",
        "domainId": "14035",
        "cliente": "SOLANGE BARBOSA DE ALMEIDA",
        "clienteDoc": "71774351153",
        "cidade": "FORMOSA",
        "uf": "GO",
        "status": "OBJETO CRIADO",
        "data": "2026-05-05",
        "postagem": 35.26,
        "remetente": "ANNE BLE1NC",
        "valorDeclarado": 456.0
      },
      "1893722_10": {
        "codigoVolume": "1893722_10",
        "orderNumber": "10",
        "domainId": "1893722",
        "cliente": "KELLY GOMES TOMELIN",
        "clienteDoc": "41264100000102",
        "cidade": "SINOP",
        "uf": "MT",
        "status": "ENCAMINHADO PARA O OPERADOR LOGÍSTICO",
        "data": "2026-05-05",
        "postagem": 36.16,
        "remetente": "SARA E MARI",
        "valorDeclarado": 515.6
      },
      "14035_6277": {
        "codigoVolume": "14035_6277",
        "orderNumber": "6277",
        "domainId": "14035",
        "cliente": "JE9SSICA KELI BASTOS",
        "clienteDoc": "40281926840",
        "cidade": "POE7OS DE CALDAS",
        "uf": "MG",
        "status": "OBJETO CRIADO",
        "data": "2026-05-05",
        "postagem": 18.41,
        "remetente": "ANNE BLE1NC",
        "valorDeclarado": 316.0
      },
      "1956465_205": {
        "codigoVolume": "1956465_205",
        "orderNumber": "205",
        "domainId": "1956465",
        "cliente": "JAQUELINE",
        "clienteDoc": "12884123717",
        "cidade": "PRESIDENTE KENNEDY",
        "uf": "ES",
        "status": "OBJETO CRIADO",
        "data": "2026-05-05",
        "postagem": 19.5,
        "remetente": "PORE3",
        "valorDeclarado": 305.0
      },
      "1439966_10": {
        "codigoVolume": "1439966_10",
        "orderNumber": "10",
        "domainId": "1439966",
        "cliente": "ADRIANA PERES",
        "clienteDoc": "21359424806",
        "cidade": "BOITUVA",
        "uf": "SP",
        "status": "OBJETO CRIADO",
        "data": "2026-05-05",
        "postagem": 28.16,
        "remetente": "LIBERF4 STYLE",
        "valorDeclarado": 420.0
      },
      "1737229_893": {
        "codigoVolume": "1737229_893",
        "orderNumber": "893",
        "domainId": "1737229",
        "cliente": "PRISCILA M A DARINI",
        "clienteDoc": "22002152829",
        "cidade": "RIBEIRE3O PRETO",
        "uf": "SP",
        "status": "OBJETO CRIADO",
        "data": "2026-05-05",
        "postagem": 15.63,
        "remetente": "KAESSI",
        "valorDeclarado": 385.0
      },
      "1355848_4188": {
        "codigoVolume": "1355848_4188",
        "orderNumber": "4188",
        "domainId": "1355848",
        "cliente": "JUAREZ BATISTA ALVES",
        "clienteDoc": "48916474000104",
        "cidade": "SE3O VICENTE",
        "uf": "SP",
        "status": "OBJETO POSTADO APÓS O HORÁRIO LIMITE DA UNIDADE",
        "data": "2026-05-05",
        "postagem": 30.12,
        "remetente": "ARARY",
        "valorDeclarado": 1231.0
      },
      "1956465_208": {
        "codigoVolume": "1956465_208",
        "orderNumber": "208",
        "domainId": "1956465",
        "cliente": "MARIA SINEIDE",
        "clienteDoc": "33222063869",
        "cidade": "PRAIA GRANDE",
        "uf": "SP",
        "status": "OBJETO CRIADO",
        "data": "2026-05-05",
        "postagem": 15.48,
        "remetente": "PORE3",
        "valorDeclarado": 304.0
      },
      "268016_6749": {
        "codigoVolume": "268016_6749",
        "orderNumber": "6749",
        "domainId": "268016",
        "cliente": "LUANA RODRIGUES E RODRIGUES",
        "clienteDoc": "34948728000161",
        "cidade": "SE3O LUEDS",
        "uf": "MA",
        "status": "OBJETO CRIADO",
        "data": "2026-05-05",
        "postagem": 29.2,
        "remetente": "CHOCOLATE DOCE",
        "valorDeclarado": 460.0
      },
      "1355848_4183": {
        "codigoVolume": "1355848_4183",
        "orderNumber": "4183",
        "domainId": "1355848",
        "cliente": "YONARA DA SILVA NOVO SULTAN",
        "clienteDoc": "59709090259",
        "cidade": "MANAUS",
        "uf": "AM",
        "status": "ARQUIVO RECEBIDO",
        "data": "2026-05-05",
        "postagem": 221.4,
        "remetente": "ARARY",
        "valorDeclarado": 1073.0
      },
      "14035_6283": {
        "codigoVolume": "14035_6283",
        "orderNumber": "6283",
        "domainId": "14035",
        "cliente": "GATTA VESTUE1RIOS LTDA",
        "clienteDoc": "58311862000115",
        "cidade": "CRAVINHOS",
        "uf": "SP",
        "status": "OBJETO CRIADO",
        "data": "2026-05-05",
        "postagem": 15.37,
        "remetente": "ANNE BLE1NC",
        "valorDeclarado": 268.0
      },
      "1355848_4189": {
        "codigoVolume": "1355848_4189",
        "orderNumber": "4189",
        "domainId": "1355848",
        "cliente": "AYONARA C C SANTOS FERREIRA FERREIRA",
        "clienteDoc": "00746034423",
        "cidade": "RECIFE",
        "uf": "PE",
        "status": "OBJETO EM TRANSFERÊNCIA - POR FAVOR AGUARDE",
        "data": "2026-05-05",
        "postagem": 91.0,
        "remetente": "ARARY",
        "valorDeclarado": 763.0
      },
      "1562486_4": {
        "codigoVolume": "1562486_4",
        "orderNumber": "4",
        "domainId": "1562486",
        "cliente": "USUC1RIO TESTE VESTI",
        "clienteDoc": "81803653000100",
        "cidade": "RIO GRANDE DA SERRA",
        "uf": "SP",
        "status": "OBJETO CRIADO",
        "data": "2026-05-05",
        "postagem": 31.46,
        "remetente": "ASHA PLUS",
        "valorDeclarado": 1500.0
      },
      "14035_6284": {
        "codigoVolume": "14035_6284",
        "orderNumber": "6284",
        "domainId": "14035",
        "cliente": "ANE NOGUTI",
        "clienteDoc": "21854884816",
        "cidade": "SE3O GONE7ALO",
        "uf": "RJ",
        "status": "OBJETO CRIADO",
        "data": "2026-05-05",
        "postagem": 57.51,
        "remetente": "ANNE BLE1NC",
        "valorDeclarado": 732.0
      },
      "2032548_3": {
        "codigoVolume": "2032548_3",
        "orderNumber": "3",
        "domainId": "2032548",
        "cliente": "USUC1RIO TESTE VESTI",
        "clienteDoc": "81803653000100",
        "cidade": "RIO GRANDE DA SERRA",
        "uf": "SP",
        "status": "OBJETO CRIADO",
        "data": "2026-05-05",
        "postagem": 42.35,
        "remetente": "MARI MODAS",
        "valorDeclarado": 1799.8
      },
      "1737229_896": {
        "codigoVolume": "1737229_896",
        "orderNumber": "896",
        "domainId": "1737229",
        "cliente": "ANDREA M OLIVEIRA",
        "clienteDoc": "05709358819",
        "cidade": "SE3O BENTO DO SAPUCAED",
        "uf": "SP",
        "status": "OBJETO CRIADO",
        "data": "2026-05-05",
        "postagem": 52.68,
        "remetente": "KAESSI",
        "valorDeclarado": 1235.0
      },
      "14035_6285": {
        "codigoVolume": "14035_6285",
        "orderNumber": "6285",
        "domainId": "14035",
        "cliente": "GINA KARLA SOBREIRA NUNES",
        "clienteDoc": "06566973699",
        "cidade": "GOVERNADOR VALADARES",
        "uf": "MG",
        "status": "OBJETO CRIADO",
        "data": "2026-05-05",
        "postagem": 24.57,
        "remetente": "ANNE BLE1NC",
        "valorDeclarado": 480.0
      },
      "14035_6289": {
        "codigoVolume": "14035_6289",
        "orderNumber": "6289",
        "domainId": "14035",
        "cliente": "LIEAZ",
        "clienteDoc": "16638163000134",
        "cidade": "ITABIRITO",
        "uf": "MG",
        "status": "OBJETO CRIADO",
        "data": "2026-05-05",
        "postagem": 62.91,
        "remetente": "ANNE BLE1NC",
        "valorDeclarado": 1941.0
      },
      "14035_6291": {
        "codigoVolume": "14035_6291",
        "orderNumber": "6291",
        "domainId": "14035",
        "cliente": "CAROLINA REGINA DA SILVA",
        "clienteDoc": "32548718808",
        "cidade": "MAREDLIA",
        "uf": "SP",
        "status": "OBJETO CRIADO",
        "data": "2026-05-05",
        "postagem": 16.0,
        "remetente": "ANNE BLE1NC",
        "valorDeclarado": 392.0
      },
      "1956465_210": {
        "codigoVolume": "1956465_210",
        "orderNumber": "210",
        "domainId": "1956465",
        "cliente": "NATALIA TEIXEIRA DA SILVA",
        "clienteDoc": "12415307696",
        "cidade": "NOVA SERRANA",
        "uf": "MG",
        "status": "OBJETO CRIADO",
        "data": "2026-05-05",
        "postagem": 21.2,
        "remetente": "PORE3",
        "valorDeclarado": 280.0
      },
      "14035_6292": {
        "codigoVolume": "14035_6292",
        "orderNumber": "6292",
        "domainId": "14035",
        "cliente": "NEUZETE BARBOSA",
        "clienteDoc": "01988890543",
        "cidade": "SERTE3OZINHO",
        "uf": "SP",
        "status": "OBJETO CRIADO",
        "data": "2026-05-05",
        "postagem": 14.81,
        "remetente": "ANNE BLE1NC",
        "valorDeclarado": 229.0
      },
      "14035_6293": {
        "codigoVolume": "14035_6293",
        "orderNumber": "6293",
        "domainId": "14035",
        "cliente": "IVANA REIS",
        "clienteDoc": "65881087534",
        "cidade": "SANTA CRUZ CABRE1LIA",
        "uf": "BA",
        "status": "OBJETO CRIADO",
        "data": "2026-05-05",
        "postagem": 124.16,
        "remetente": "ANNE BLE1NC",
        "valorDeclarado": 2384.99
      },
      "14035_6294": {
        "codigoVolume": "14035_6294",
        "orderNumber": "6294",
        "domainId": "14035",
        "cliente": "ANDREIA LUIZ DOS SANTOS",
        "clienteDoc": "04014010651",
        "cidade": "CARAED",
        "uf": "MG",
        "status": "OBJETO CRIADO",
        "data": "2026-05-05",
        "postagem": 20.81,
        "remetente": "ANNE BLE1NC",
        "valorDeclarado": 523.0
      },
      "14035_6295": {
        "codigoVolume": "14035_6295",
        "orderNumber": "6295",
        "domainId": "14035",
        "cliente": "ELLEN BIONDI",
        "clienteDoc": "73698750597",
        "cidade": "CAMAE7ARI",
        "uf": "BA",
        "status": "OBJETO CRIADO",
        "data": "2026-05-05",
        "postagem": 26.78,
        "remetente": "ANNE BLE1NC",
        "valorDeclarado": 461.0
      },
      "1956465_211": {
        "codigoVolume": "1956465_211",
        "orderNumber": "211",
        "domainId": "1956465",
        "cliente": "VIVIAM CRISTINA FERNANDES DE SOUZA",
        "clienteDoc": "30134545800",
        "cidade": "SANTA RITA DO PASSA QUATRO",
        "uf": "SP",
        "status": "OBJETO CRIADO",
        "data": "2026-05-06",
        "postagem": 52.72,
        "remetente": "PORE3",
        "valorDeclarado": 240.0
      },
      "1305816_14": {
        "codigoVolume": "1305816_14",
        "orderNumber": "14",
        "domainId": "1305816",
        "cliente": "TESTE PEDIDO SUPORTE VESTI",
        "clienteDoc": "88174196000181",
        "cidade": "PORTO ALEGRE",
        "uf": "RS",
        "status": "OBJETO CRIADO",
        "data": "2026-05-06",
        "postagem": 23.34,
        "remetente": "PALMEIRA",
        "valorDeclarado": 519.8
      },
      "1305816_15": {
        "codigoVolume": "1305816_15",
        "orderNumber": "15",
        "domainId": "1305816",
        "cliente": "MATHEUS",
        "clienteDoc": "38155471802",
        "cidade": "SE3O PAULO",
        "uf": "SP",
        "status": "OBJETO CRIADO",
        "data": "2026-05-06",
        "postagem": 12.28,
        "remetente": "PALMEIRA",
        "valorDeclarado": 259.9
      },
      "1805647_1256": {
        "codigoVolume": "1805647_1256",
        "orderNumber": "1256",
        "domainId": "1805647",
        "cliente": "FRANCINELI ALCALE1",
        "clienteDoc": "31035734800",
        "cidade": "SANTA BE1RBARA D'OESTE",
        "uf": "SP",
        "status": "OBJETO POSTADO APÓS O HORÁRIO LIMITE DA UNIDADE",
        "data": "2026-05-06",
        "postagem": 14.3,
        "remetente": "CVL MODA - PLAZA POLO",
        "valorDeclarado": 261.4
      },
      "1355848_4193": {
        "codigoVolume": "1355848_4193",
        "orderNumber": "4193",
        "domainId": "1355848",
        "cliente": "LUCILENE VALERIA DA SILVA",
        "clienteDoc": "30253775000130",
        "cidade": "BETIM",
        "uf": "MG",
        "status": "ENTRADA NO CENTRO DE DISTRIBUIÇÃO",
        "data": "2026-05-06",
        "postagem": 20.93,
        "remetente": "ARARY",
        "valorDeclarado": 734.0
      },
      "14035_6262": {
        "codigoVolume": "14035_6262",
        "orderNumber": "6262",
        "domainId": "14035",
        "cliente": "IVANA MEDEIROS",
        "clienteDoc": "43043022000141",
        "cidade": "RECIFE",
        "uf": "PE",
        "status": "TRANSFERENCIA",
        "data": "2026-05-06",
        "postagem": 56.67,
        "remetente": "ANNE BLE1NC",
        "valorDeclarado": 500.0
      },
      "268016_6750": {
        "codigoVolume": "268016_6750",
        "orderNumber": "6750",
        "domainId": "268016",
        "cliente": "GIOVANNA YARZON",
        "clienteDoc": "55335196000167",
        "cidade": "CAMPO GRANDE",
        "uf": "MS",
        "status": "OBJETO POSTADO APÓS O HORÁRIO LIMITE DA UNIDADE",
        "data": "2026-05-06",
        "postagem": 37.21,
        "remetente": "CHOCOLATE DOCE",
        "valorDeclarado": 620.0
      },
      "14035_6296": {
        "codigoVolume": "14035_6296",
        "orderNumber": "6296",
        "domainId": "14035",
        "cliente": "BRUNA TAISLA",
        "clienteDoc": "10651693616",
        "cidade": "LAVRAS",
        "uf": "MG",
        "status": "OBJETO CRIADO",
        "data": "2026-05-06",
        "postagem": 25.66,
        "remetente": "ANNE BLE1NC",
        "valorDeclarado": 587.0
      },
      "14035_6297": {
        "codigoVolume": "14035_6297",
        "orderNumber": "6297",
        "domainId": "14035",
        "cliente": "ANDREZZA SARCINELLI",
        "clienteDoc": "14530934780",
        "cidade": "VILA VELHA",
        "uf": "ES",
        "status": "OBJETO CRIADO",
        "data": "2026-05-06",
        "postagem": 18.14,
        "remetente": "ANNE BLE1NC",
        "valorDeclarado": 328.0
      },
      "14035_6298": {
        "codigoVolume": "14035_6298",
        "orderNumber": "6298",
        "domainId": "14035",
        "cliente": "KATIA PEDRA",
        "clienteDoc": "01490124110",
        "cidade": "CAMPO GRANDE",
        "uf": "MS",
        "status": "OBJETO CRIADO",
        "data": "2026-05-06",
        "postagem": 36.96,
        "remetente": "ANNE BLE1NC",
        "valorDeclarado": 551.0
      },
      "268016_6751": {
        "codigoVolume": "268016_6751",
        "orderNumber": "6751",
        "domainId": "268016",
        "cliente": "INDIANA SAN FERREIRA",
        "clienteDoc": "43763542000129",
        "cidade": "PORTO SEGURO",
        "uf": "BA",
        "status": "OBJETO EM TRANSFERÊNCIA - POR FAVOR AGUARDE",
        "data": "2026-05-06",
        "postagem": 66.67,
        "remetente": "CHOCOLATE DOCE",
        "valorDeclarado": 515.0
      },
      "1956465_215": {
        "codigoVolume": "1956465_215",
        "orderNumber": "215",
        "domainId": "1956465",
        "cliente": "MARIA SANTOS",
        "clienteDoc": "76944310082",
        "cidade": "GRAVATAED",
        "uf": "RS",
        "status": "OBJETO CRIADO",
        "data": "2026-05-06",
        "postagem": 20.72,
        "remetente": "PORE3",
        "valorDeclarado": 201.0
      },
      "1355848_4194": {
        "codigoVolume": "1355848_4194",
        "orderNumber": "4194",
        "domainId": "1355848",
        "cliente": "SILVANA ESCOBAR DE VASTO",
        "clienteDoc": "32174296000153",
        "cidade": "SOROCABA",
        "uf": "SP",
        "status": "ENTRADA NO CENTRO DE DISTRIBUIÇÃO",
        "data": "2026-05-06",
        "postagem": 15.09,
        "remetente": "ARARY",
        "valorDeclarado": 382.0
      },
      "14035_6300": {
        "codigoVolume": "14035_6300",
        "orderNumber": "6300",
        "domainId": "14035",
        "cliente": "JAMILA STOCO GOBBI JOSE",
        "clienteDoc": "06881444702",
        "cidade": "VITF3RIA",
        "uf": "ES",
        "status": "OBJETO CRIADO",
        "data": "2026-05-06",
        "postagem": 17.94,
        "remetente": "ANNE BLE1NC",
        "valorDeclarado": 350.0
      },
      "14035_6304": {
        "codigoVolume": "14035_6304",
        "orderNumber": "6304",
        "domainId": "14035",
        "cliente": "NATE1LIA CORREIA",
        "clienteDoc": "03336228123",
        "cidade": "BRASEDLIA",
        "uf": "DF",
        "status": "OBJETO CRIADO",
        "data": "2026-05-06",
        "postagem": 40.04,
        "remetente": "ANNE BLE1NC",
        "valorDeclarado": 957.0
      },
      "268016_6752": {
        "codigoVolume": "268016_6752",
        "orderNumber": "6752",
        "domainId": "268016",
        "cliente": "MARCELY VALESCA DA SILVA CARDOSO",
        "clienteDoc": "54990271000160",
        "cidade": "MACAPE1",
        "uf": "AP",
        "status": "OBJETO CRIADO",
        "data": "2026-05-06",
        "postagem": 50.73,
        "remetente": "CHOCOLATE DOCE",
        "valorDeclarado": 1292.0
      },
      "14035_6306": {
        "codigoVolume": "14035_6306",
        "orderNumber": "6306",
        "domainId": "14035",
        "cliente": "NATALIA PESSOA",
        "clienteDoc": "08017624646",
        "cidade": "CAETE9",
        "uf": "MG",
        "status": "OBJETO CRIADO",
        "data": "2026-05-06",
        "postagem": 23.43,
        "remetente": "ANNE BLE1NC",
        "valorDeclarado": 505.0
      },
      "14035_6308": {
        "codigoVolume": "14035_6308",
        "orderNumber": "6308",
        "domainId": "14035",
        "cliente": "EDUARDA LIMA",
        "clienteDoc": "62523484000100",
        "cidade": "FRANCA",
        "uf": "SP",
        "status": "OBJETO CRIADO",
        "data": "2026-05-06",
        "postagem": 17.27,
        "remetente": "ANNE BLE1NC",
        "valorDeclarado": 696.0
      },
      "14035_6309": {
        "codigoVolume": "14035_6309",
        "orderNumber": "6309",
        "domainId": "14035",
        "cliente": "LAURA DE ALMEIDA MAGALHAES FURTADO MIRANDA",
        "clienteDoc": "02187705617",
        "cidade": "RIO DE JANEIRO",
        "uf": "RJ",
        "status": "ETIQUETA EMITIDA",
        "data": "2026-05-06",
        "postagem": 59.52,
        "remetente": "ANNE BLE1NC",
        "valorDeclarado": 933.0
      },
      "14035_6315": {
        "codigoVolume": "14035_6315",
        "orderNumber": "6315",
        "domainId": "14035",
        "cliente": "VANESSA LISBOA",
        "clienteDoc": "31267163852",
        "cidade": "AMPARO",
        "uf": "SP",
        "status": "OBJETO CRIADO",
        "data": "2026-05-06",
        "postagem": 31.26,
        "remetente": "ANNE BLE1NC",
        "valorDeclarado": 506.0
      },
      "1355848_4195": {
        "codigoVolume": "1355848_4195",
        "orderNumber": "4195",
        "domainId": "1355848",
        "cliente": "OLIVEIRA",
        "clienteDoc": "03167504170",
        "cidade": "BRASEDLIA",
        "uf": "DF",
        "status": "OBJETO CRIADO",
        "data": "2026-05-07",
        "postagem": 31.87,
        "remetente": "ARARY",
        "valorDeclarado": 620.0
      },
      "14035_6320": {
        "codigoVolume": "14035_6320",
        "orderNumber": "6320",
        "domainId": "14035",
        "cliente": "MICHELE SILVA",
        "clienteDoc": "76936503691",
        "cidade": "BELO HORIZONTE",
        "uf": "MG",
        "status": "OBJETO CRIADO",
        "data": "2026-05-07",
        "postagem": 19.95,
        "remetente": "ANNE BLE1NC",
        "valorDeclarado": 316.0
      }
    },
    "paVesti": [
      {
        "data": "2026-05-06",
        "operador": "ONLOG RED",
        "modalidade": "ECONOPACK",
        "codigoInterno": "AA0097914325",
        "numeroNF": "11078758",
        "remetente": "PA VESTI",
        "cliente": "MARIA APARECIDA SANTANA LIMA",
        "clienteDoc": "22.982.386/0001-17",
        "cidade": "ILHÉUS",
        "uf": "BA",
        "status": "OBJETO EM TRANSFERÊNCIA - POR FAVOR AGUARDE",
        "postagem": 104.32
      },
      {
        "data": "2026-05-04",
        "operador": "ONLOG RED",
        "modalidade": "FASTPACK",
        "codigoInterno": "AA0097677950",
        "numeroNF": "009728685",
        "remetente": "PA VESTI",
        "cliente": "MARIANA BERNARDI JOIA",
        "clienteDoc": "08.143.870/0001-21",
        "cidade": "BRASÍLIA",
        "uf": "DF",
        "status": "ETIQUETA EMITIDA",
        "postagem": 68.27
      },
      {
        "data": "2026-05-04",
        "operador": "ONLOG RED",
        "modalidade": "ECONOPACK",
        "codigoInterno": "AA0097678427",
        "numeroNF": "007135648",
        "remetente": "VESTI",
        "cliente": "MARIA APARECIDA SANTANA LIMA",
        "clienteDoc": "22982386000117",
        "cidade": "ILHEUS",
        "uf": "BA",
        "status": "ETIQUETA EMITIDA",
        "postagem": 104.32
      }
    ]
  }
}